mikettle/__init__.py
mikettle/mikettle.py
mikettle-0.0.2.dist-info/LICENSE
mikettle-0.0.2.dist-info/METADATA
mikettle-0.0.2.dist-info/WHEEL
mikettle-0.0.2.dist-info/top_level.txt
mikettle-0.0.2.dist-info/RECORD
